vtoa/__init__.py
vtoa/cli.py
vtoa/converter.py
vtoa/player.py
vtoa-0.1.0.dist-info/licenses/LICENSE
vtoa-0.1.0.dist-info/METADATA
vtoa-0.1.0.dist-info/WHEEL
vtoa-0.1.0.dist-info/entry_points.txt
vtoa-0.1.0.dist-info/top_level.txt
vtoa-0.1.0.dist-info/RECORD
