Metadata-Version: 2.4
Name: vtoa
Version: 0.1.0
Summary: Convert any video to ASCII art playable in your terminal
Author-email: Tanmay Sachan <tnmysachan@gmail.com>
License-Expression: MIT
Project-URL: Homepage, https://github.com/yourusername/vtoa
Project-URL: Repository, https://github.com/yourusername/vtoa
Keywords: video,ascii,terminal,cli,art
Classifier: Development Status :: 4 - Beta
Classifier: Environment :: Console
Classifier: Intended Audience :: Developers
Classifier: Programming Language :: Python :: 3
Classifier: Programming Language :: Python :: 3.8
Classifier: Programming Language :: Python :: 3.9
Classifier: Programming Language :: Python :: 3.10
Classifier: Programming Language :: Python :: 3.11
Classifier: Programming Language :: Python :: 3.12
Classifier: Topic :: Multimedia :: Video
Classifier: Topic :: Artistic Software
Requires-Python: >=3.8
License-File: LICENSE
Requires-Dist: opencv-python>=4.5.0
Requires-Dist: numpy>=1.19.0
Requires-Dist: yt-dlp>=2023.0.0
Provides-Extra: dev
Requires-Dist: pytest>=7.0.0; extra == "dev"
Requires-Dist: black>=23.0.0; extra == "dev"
Requires-Dist: ruff>=0.1.0; extra == "dev"
Dynamic: license-file
